ck/__init__.py
charan-0.1.0.dist-info/METADATA
charan-0.1.0.dist-info/WHEEL
charan-0.1.0.dist-info/top_level.txt
charan-0.1.0.dist-info/RECORD
