Metadata-Version: 2.1
Name: charan
Version: 0.1.0
Summary: A simple ck module with basic functions
Home-page: https://github.com/charankosari
Author: Charan Kosari
Author-email: shivacharankosari099@gmail.com
Classifier: Programming Language :: Python :: 3
Classifier: License :: OSI Approved :: MIT License
Classifier: Operating System :: OS Independent
Requires-Python: >=3.6
